{"attempt":1,"conclusion":"failure","createdAt":"2025-02-13T08:20:52Z","databaseId":13303339241,"displayTitle":"H34 modulo iac kaos","event":"pull_request","headBranch":"H34-modulo-iac-kaos","headSha":"69b973846e3d19e51bee5d9c1fbecdbbedcc486f","jobs":[{"completedAt":"2025-02-13T08:21:18Z","conclusion":"failure","databaseId":37148752503,"name":"job-core","startedAt":"2025-02-13T08:21:10Z","status":"completed","steps":[{"completedAt":"2025-02-13T08:21:10Z","conclusion":"success","name":"Set up job","number":1,"startedAt":"2025-02-13T08:21:09Z","status":"completed"},{"completedAt":"2025-02-13T08:21:11Z","conclusion":"success","name":"Checkout code","number":2,"startedAt":"2025-02-13T08:21:10Z","status":"completed"},{"completedAt":"2025-02-13T08:21:12Z","conclusion":"success","name":"Validate file extensions","number":3,"startedAt":"2025-02-13T08:21:12Z","status":"completed"},{"completedAt":"2025-02-13T08:21:12Z","conclusion":"success","name":"Crear JSON","number":4,"startedAt":"2025-02-13T08:21:12Z","status":"completed"},{"completedAt":"2025-02-13T08:21:12Z","conclusion":"success","name":"Set environment variable for ref","number":5,"startedAt":"2025-02-13T08:21:12Z","status":"completed"},{"completedAt":"2025-02-13T08:21:12Z","conclusion":"failure","name":"Upload Files","number":6,"startedAt":"2025-02-13T08:21:12Z","status":"completed"},{"completedAt":"2025-02-13T08:21:12Z","conclusion":"skipped","name":"Ver JSON","number":7,"startedAt":"2025-02-13T08:21:12Z","status":"completed"},{"completedAt":"2025-02-13T08:21:12Z","conclusion":"skipped","name":"Run # Nuevo proceso de activacion de los modulos","number":8,"startedAt":"2025-02-13T08:21:12Z","status":"completed"},{"completedAt":"2025-02-13T08:21:12Z","conclusion":"success","name":"Post Checkout code","number":16,"startedAt":"2025-02-13T08:21:12Z","status":"completed"},{"completedAt":"2025-02-13T08:21:12Z","conclusion":"success","name":"Complete job","number":17,"startedAt":"2025-02-13T08:21:12Z","status":"completed"}],"url":"https://github.com/Ka0s-Klaus/ka0s/actions/runs/13303339241/job/37148752503"},{"completedAt":"2025-02-13T08:21:20Z","conclusion":"skipped","databaseId":37148774390,"name":"handle-success","startedAt":"2025-02-13T08:21:20Z","status":"completed","steps":[],"url":"https://github.com/Ka0s-Klaus/ka0s/actions/runs/13303339241/job/37148774390"},{"completedAt":"2025-02-13T08:21:34Z","conclusion":"success","databaseId":37148774873,"name":"handle_failure","startedAt":"2025-02-13T08:21:26Z","status":"completed","steps":[{"completedAt":"2025-02-13T08:21:25Z","conclusion":"success","name":"Set up job","number":1,"startedAt":"2025-02-13T08:21:25Z","status":"completed"},{"completedAt":"2025-02-13T08:21:25Z","conclusion":"success","name":"handle-failure-execution","number":2,"startedAt":"2025-02-13T08:21:25Z","status":"completed"},{"completedAt":"2025-02-13T08:21:26Z","conclusion":"success","name":"Complete job","number":3,"startedAt":"2025-02-13T08:21:25Z","status":"completed"}],"url":"https://github.com/Ka0s-Klaus/ka0s/actions/runs/13303339241/job/37148774873"},{"completedAt":"2025-02-13T08:21:47Z","conclusion":"success","databaseId":37148786728,"name":"end-workflow","startedAt":"2025-02-13T08:21:41Z","status":"completed","steps":[{"completedAt":"2025-02-13T08:21:41Z","conclusion":"success","name":"Set up job","number":1,"startedAt":"2025-02-13T08:21:40Z","status":"completed"},{"completedAt":"2025-02-13T08:21:42Z","conclusion":"success","name":"Checkout code","number":2,"startedAt":"2025-02-13T08:21:41Z","status":"completed"},{"completedAt":"2025-02-13T08:21:43Z","conclusion":"success","name":"Finaliza el workflow","number":3,"startedAt":"2025-02-13T08:21:42Z","status":"completed"},{"completedAt":"2025-02-13T08:21:47Z","conclusion":"success","name":"Post Checkout code","number":6,"startedAt":"2025-02-13T08:21:47Z","status":"completed"},{"completedAt":"2025-02-13T08:21:43Z","conclusion":"success","name":"Complete job","number":7,"startedAt":"2025-02-13T08:21:43Z","status":"completed"}],"url":"https://github.com/Ka0s-Klaus/ka0s/actions/runs/13303339241/job/37148786728"}],"name":"Ka0s","number":296,"startedAt":"2025-02-13T08:20:52Z","status":"completed","updatedAt":"2025-02-13T08:21:49Z","url":"https://github.com/Ka0s-Klaus/ka0s/actions/runs/13303339241","workflowDatabaseId":142022472,"workflowName":"Ka0s"}
