{"conclusion":"success","createdAt":"2025-02-25T17:05:27Z","databaseId":13526800010,"displayTitle":"Ka0s Markdown Lint","event":"workflow_dispatch","headBranch":"H34-modulo-iac-kaos","headSha":"a9b5e21a63773600907ecf54e59cb2d611ffd6d1","jobs":[{"completedAt":"2025-02-25T17:05:48Z","conclusion":"success","databaseId":37799310662,"name":"job-core","startedAt":"2025-02-25T17:05:36Z","status":"completed","steps":[{"completedAt":"2025-02-25T17:05:36Z","conclusion":"success","name":"Set up job","number":1,"startedAt":"2025-02-25T17:05:35Z","status":"completed"},{"completedAt":"2025-02-25T17:05:38Z","conclusion":"success","name":"Run actions/checkout@v4","number":2,"startedAt":"2025-02-25T17:05:36Z","status":"completed"},{"completedAt":"2025-02-25T17:05:38Z","conclusion":"success","name":"Run actions/setup-node@v4","number":3,"startedAt":"2025-02-25T17:05:38Z","status":"completed"},{"completedAt":"2025-02-25T17:05:42Z","conclusion":"success","name":"Run npm install -g markdownlint-cli2","number":4,"startedAt":"2025-02-25T17:05:39Z","status":"completed"},{"completedAt":"2025-02-25T17:05:44Z","conclusion":"success","name":"Run # Realizamos el check del documento md ","number":5,"startedAt":"2025-02-25T17:05:42Z","status":"completed"},{"completedAt":"2025-02-25T17:05:48Z","conclusion":"success","name":"Post Run actions/setup-node@v4","number":9,"startedAt":"2025-02-25T17:05:48Z","status":"completed"},{"completedAt":"2025-02-25T17:05:48Z","conclusion":"success","name":"Post Run actions/checkout@v4","number":10,"startedAt":"2025-02-25T17:05:48Z","status":"completed"},{"completedAt":"2025-02-25T17:05:44Z","conclusion":"success","name":"Complete job","number":11,"startedAt":"2025-02-25T17:05:44Z","status":"completed"}],"url":"https://github.com/Ka0s-Klaus/ka0s/actions/runs/13526800010/job/37799310662"},{"completedAt":"2025-02-25T17:05:57Z","conclusion":"success","databaseId":37799333654,"name":"handle-success","startedAt":"2025-02-25T17:05:53Z","status":"completed","steps":[{"completedAt":"2025-02-25T17:05:53Z","conclusion":"success","name":"Set up job","number":1,"startedAt":"2025-02-25T17:05:53Z","status":"completed"},{"completedAt":"2025-02-25T17:05:53Z","conclusion":"success","name":"handle-success-execution","number":2,"startedAt":"2025-02-25T17:05:53Z","status":"completed"},{"completedAt":"2025-02-25T17:05:53Z","conclusion":"success","name":"Complete job","number":3,"startedAt":"2025-02-25T17:05:53Z","status":"completed"}],"url":"https://github.com/Ka0s-Klaus/ka0s/actions/runs/13526800010/job/37799333654"},{"completedAt":"2025-02-25T17:06:09Z","conclusion":"success","databaseId":37799344155,"name":"end-workflow","startedAt":"2025-02-25T17:06:02Z","status":"completed","steps":[{"completedAt":"2025-02-25T17:06:02Z","conclusion":"success","name":"Set up job","number":1,"startedAt":"2025-02-25T17:06:02Z","status":"completed"},{"completedAt":"2025-02-25T17:06:03Z","conclusion":"success","name":"Checkout code","number":2,"startedAt":"2025-02-25T17:06:02Z","status":"completed"},{"completedAt":"2025-02-25T17:06:07Z","conclusion":"success","name":"Finaliza el workflow","number":3,"startedAt":"2025-02-25T17:06:04Z","status":"completed"},{"completedAt":"2025-02-25T17:06:09Z","conclusion":"success","name":"Post Checkout code","number":6,"startedAt":"2025-02-25T17:06:09Z","status":"completed"},{"completedAt":"2025-02-25T17:06:07Z","conclusion":"success","name":"Complete job","number":7,"startedAt":"2025-02-25T17:06:07Z","status":"completed"}],"url":"https://github.com/Ka0s-Klaus/ka0s/actions/runs/13526800010/job/37799344155"},{"completedAt":"2025-02-25T17:05:58Z","conclusion":"skipped","databaseId":37799344564,"name":"handle_failure","startedAt":"2025-02-25T17:05:58Z","status":"completed","steps":[],"url":"https://github.com/Ka0s-Klaus/ka0s/actions/runs/13526800010/job/37799344564"}],"name":"Ka0s Markdown Lint","number":7,"startedAt":"2025-02-25T17:05:27Z","status":"completed","updatedAt":"2025-02-25T17:06:11Z","url":"https://github.com/Ka0s-Klaus/ka0s/actions/runs/13526800010","workflowDatabaseId":142215142,"workflowName":"Ka0s Markdown Lint"}
