{"conclusion":"success","createdAt":"2025-03-28T10:39:34Z","databaseId":14127148519,"displayTitle":"Ka0s JSON Lint","event":"workflow_dispatch","headBranch":"H220-web-de-resultados","headSha":"667d24c6dd0304c05a07af81759e92109ed18caf","jobs":[{"completedAt":"2025-03-28T10:39:59Z","conclusion":"success","databaseId":39578678198,"name":"job-core","startedAt":"2025-03-28T10:39:36Z","status":"completed","steps":[{"conclusion":"success","name":"Set up job","number":1,"status":"completed"},{"conclusion":"success","name":"Checkout code","number":2,"status":"completed"},{"conclusion":"success","name":"Install Node.js","number":3,"status":"completed"},{"conclusion":"success","name":"Install jsonlint","number":4,"status":"completed"},{"conclusion":"success","name":"Check JSON","number":5,"status":"completed"},{"conclusion":"success","name":"Post Install Node.js","number":9,"status":"completed"},{"conclusion":"success","name":"Post Checkout code","number":10,"status":"completed"},{"conclusion":"success","name":"Complete job","number":11,"status":"completed"}],"url":"https://github.com/Ka0s-Klaus/ka0s/actions/runs/14127148519/job/39578678198"},{"completedAt":"2025-03-28T10:41:34Z","conclusion":"success","databaseId":39578699989,"name":"handle-success","startedAt":"2025-03-28T10:41:19Z","status":"completed","steps":[{"conclusion":"success","name":"Set up job","number":1,"status":"completed"},{"conclusion":"success","name":"Checkout code","number":2,"status":"completed"},{"conclusion":"success","name":"handle-success-execution","number":3,"status":"completed"},{"conclusion":"success","name":"Post Checkout code","number":6,"status":"completed"},{"conclusion":"success","name":"Complete job","number":7,"status":"completed"}],"url":"https://github.com/Ka0s-Klaus/ka0s/actions/runs/14127148519/job/39578699989"},{"completedAt":"2025-03-28T10:43:05Z","conclusion":"success","databaseId":39578782473,"name":"end-workflow","startedAt":"2025-03-28T10:42:49Z","status":"completed","steps":[{"conclusion":"success","name":"Set up job","number":1,"status":"completed"},{"conclusion":"success","name":"Checkout code","number":2,"status":"completed"},{"conclusion":"success","name":"Finaliza el workflow","number":3,"status":"completed"},{"conclusion":"success","name":"Post Checkout code","number":6,"status":"completed"},{"conclusion":"success","name":"Complete job","number":7,"status":"completed"}],"url":"https://github.com/Ka0s-Klaus/ka0s/actions/runs/14127148519/job/39578782473"},{"completedAt":"2025-03-28T10:41:34Z","conclusion":"skipped","databaseId":39578782557,"name":"handle_failure","startedAt":"2025-03-28T10:41:34Z","status":"completed","steps":[],"url":"https://github.com/Ka0s-Klaus/ka0s/actions/runs/14127148519/job/39578782557"}],"name":"Ka0s JSON Lint","number":429,"startedAt":"2025-03-28T10:39:34Z","status":"completed","updatedAt":"2025-03-28T10:43:06Z","url":"https://github.com/Ka0s-Klaus/ka0s/actions/runs/14127148519","workflowDatabaseId":152110813,"workflowName":"Ka0s JSON Lint"}
