{"conclusion":"failure","createdAt":"2025-04-10T09:53:27Z","databaseId":14377557583,"displayTitle":"JSON","event":"push","headBranch":"H306-ficheros-de-estadisticas","headSha":"b6645a7293c777885620acac256454ccf8cd4762","jobs":[{"completedAt":"2025-04-23T10:41:53Z","conclusion":"failure","databaseId":41004710190,"name":"job-core","startedAt":"2025-04-23T10:41:45Z","status":"completed","steps":[{"conclusion":"success","name":"Set up job","number":1,"status":"completed"},{"conclusion":"success","name":"Checkout code","number":2,"status":"completed"},{"conclusion":"success","name":"Validate file extensions","number":3,"status":"completed"},{"conclusion":"success","name":"Crear JSON","number":4,"status":"completed"},{"conclusion":"success","name":"Set environment variable for ref","number":5,"status":"completed"},{"conclusion":"failure","name":"Upload Files","number":6,"status":"completed"},{"conclusion":"skipped","name":"Run git diff --name-only ebc126cfbd1c6ad72cc789db0ffc2c8ecd2b08bc b6645a7293c777885620acac256454ccf8cd4762 > files-in-commit.txt","number":7,"status":"completed"},{"conclusion":"success","name":"Post Checkout code","number":14,"status":"completed"},{"conclusion":"success","name":"Complete job","number":15,"status":"completed"}],"url":"https://github.com/Ka0s-Klaus/ka0s/actions/runs/14377557583/job/41004710190"},{"completedAt":"2025-04-23T10:53:31Z","conclusion":"success","databaseId":41004750958,"name":"handle_failure","startedAt":"2025-04-23T10:52:33Z","status":"completed","steps":[{"conclusion":"success","name":"Set up job","number":1,"status":"completed"},{"conclusion":"success","name":"Checkout code","number":2,"status":"completed"},{"conclusion":"success","name":"handle-failure-execution","number":3,"status":"completed"},{"conclusion":"success","name":"Post Checkout code","number":6,"status":"completed"},{"conclusion":"success","name":"Complete job","number":7,"status":"completed"}],"url":"https://github.com/Ka0s-Klaus/ka0s/actions/runs/14377557583/job/41004750958"},{"completedAt":"2025-04-23T10:41:54Z","conclusion":"skipped","databaseId":41004750986,"name":"handle-success","startedAt":"2025-04-23T10:41:54Z","status":"completed","steps":[],"url":"https://github.com/Ka0s-Klaus/ka0s/actions/runs/14377557583/job/41004750986"},{"completedAt":"2025-04-23T10:54:11Z","conclusion":"success","databaseId":41005393441,"name":"end-workflow","startedAt":"2025-04-23T10:54:03Z","status":"completed","steps":[{"conclusion":"success","name":"Set up job","number":1,"status":"completed"},{"conclusion":"success","name":"Checkout code","number":2,"status":"completed"},{"conclusion":"success","name":"Finaliza el workflow","number":3,"status":"completed"},{"conclusion":"success","name":"Post Checkout code","number":6,"status":"completed"},{"conclusion":"success","name":"Complete job","number":7,"status":"completed"}],"url":"https://github.com/Ka0s-Klaus/ka0s/actions/runs/14377557583/job/41005393441"}],"name":"Ka0s","number":1130,"startedAt":"2025-04-23T10:41:10Z","status":"completed","updatedAt":"2025-04-23T10:54:12Z","url":"https://github.com/Ka0s-Klaus/ka0s/actions/runs/14377557583","workflowDatabaseId":142022472,"workflowName":"Ka0s"}
