{"conclusion":"failure","createdAt":"2025-04-24T08:31:17Z","databaseId":14637086440,"displayTitle":"Ka0s Markdown Lint","event":"workflow_dispatch","headBranch":"H44-creación-módulo-versionado","headSha":"2a5cae22de7d1979f8a8f9aacf138b417ce24a5f","jobs":[{"completedAt":"2025-04-24T08:36:15Z","conclusion":"cancelled","databaseId":41070586609,"name":"job-core","startedAt":"2025-04-24T08:31:18Z","status":"completed","steps":[],"url":"https://github.com/Ka0s-Klaus/ka0s/actions/runs/14637086440/job/41070586609"},{"completedAt":"2025-04-24T08:36:15Z","conclusion":"skipped","databaseId":41070884973,"name":"handle_failure","startedAt":"2025-04-24T08:36:15Z","status":"completed","steps":[],"url":"https://github.com/Ka0s-Klaus/ka0s/actions/runs/14637086440/job/41070884973"},{"completedAt":"2025-04-24T08:37:53Z","conclusion":"success","databaseId":41070884976,"name":"end-workflow","startedAt":"2025-04-24T08:37:09Z","status":"completed","steps":[{"conclusion":"success","name":"Set up job","number":1,"status":"completed"},{"conclusion":"success","name":"Checkout code","number":2,"status":"completed"},{"conclusion":"success","name":"Finaliza el workflow","number":3,"status":"completed"},{"conclusion":"success","name":"Post Checkout code","number":6,"status":"completed"},{"conclusion":"success","name":"Complete job","number":7,"status":"completed"}],"url":"https://github.com/Ka0s-Klaus/ka0s/actions/runs/14637086440/job/41070884976"},{"completedAt":"2025-04-24T08:36:15Z","conclusion":"skipped","databaseId":41070885162,"name":"handle-success","startedAt":"2025-04-24T08:36:15Z","status":"completed","steps":[],"url":"https://github.com/Ka0s-Klaus/ka0s/actions/runs/14637086440/job/41070885162"}],"name":"Ka0s Markdown Lint","number":147,"startedAt":"2025-04-24T08:31:17Z","status":"completed","updatedAt":"2025-04-24T08:37:54Z","url":"https://github.com/Ka0s-Klaus/ka0s/actions/runs/14637086440","workflowDatabaseId":142215142,"workflowName":"Ka0s Markdown Lint"}
