{"conclusion":"success","createdAt":"2025-05-20T06:45:03Z","databaseId":15130728901,"displayTitle":"Arreglo dashboard","event":"push","headBranch":"main","headSha":"180d2db29be318e72f01f7e41ec4d21c728b4c88","jobs":[{"completedAt":"2025-05-20T06:45:17Z","conclusion":"success","databaseId":42531067623,"name":"job-test","startedAt":"2025-05-20T06:45:05Z","status":"completed","steps":[{"conclusion":"success","name":"Set up job","number":1,"status":"completed"},{"conclusion":"success","name":"Checkout repository","number":2,"status":"completed"},{"conclusion":"success","name":"Limpiar caché local antes del despliegue","number":3,"status":"completed"},{"conclusion":"success","name":"Deploy Test Dashboard to Web Server via SFTP","number":4,"status":"completed"},{"conclusion":"success","name":"Post Checkout repository","number":8,"status":"completed"},{"conclusion":"success","name":"Complete job","number":9,"status":"completed"}],"url":"https://github.com/Ka0s-Klaus/ka0s/actions/runs/15130728901/job/42531067623"},{"completedAt":"2025-05-20T06:45:16Z","conclusion":"success","databaseId":42531067629,"name":"job-core","startedAt":"2025-05-20T06:45:05Z","status":"completed","steps":[{"conclusion":"success","name":"Set up job","number":1,"status":"completed"},{"conclusion":"success","name":"Checkout repository","number":2,"status":"completed"},{"conclusion":"success","name":"Limpiar caché local antes del despliegue","number":3,"status":"completed"},{"conclusion":"success","name":"Deploy Dashboard to Web Server via SFTP","number":4,"status":"completed"},{"conclusion":"success","name":"Post Checkout repository","number":8,"status":"completed"},{"conclusion":"success","name":"Complete job","number":9,"status":"completed"}],"url":"https://github.com/Ka0s-Klaus/ka0s/actions/runs/15130728901/job/42531067629"},{"completedAt":"2025-05-20T06:45:25Z","conclusion":"success","databaseId":42531078131,"name":"handle-success","startedAt":"2025-05-20T06:45:17Z","status":"completed","steps":[{"conclusion":"success","name":"Set up job","number":1,"status":"completed"},{"conclusion":"success","name":"Checkout code","number":2,"status":"completed"},{"conclusion":"success","name":"handle-success-execution","number":3,"status":"completed"},{"conclusion":"success","name":"Post Checkout code","number":6,"status":"completed"},{"conclusion":"success","name":"Complete job","number":7,"status":"completed"}],"url":"https://github.com/Ka0s-Klaus/ka0s/actions/runs/15130728901/job/42531078131"},{"completedAt":"2025-05-20T06:45:42Z","conclusion":"success","databaseId":42531085404,"name":"end-workflow","startedAt":"2025-05-20T06:45:35Z","status":"completed","steps":[{"conclusion":"success","name":"Set up job","number":1,"status":"completed"},{"conclusion":"success","name":"Checkout code","number":2,"status":"completed"},{"conclusion":"success","name":"Finaliza el workflow","number":3,"status":"completed"},{"conclusion":"success","name":"Post Checkout code","number":6,"status":"completed"},{"conclusion":"success","name":"Complete job","number":7,"status":"completed"}],"url":"https://github.com/Ka0s-Klaus/ka0s/actions/runs/15130728901/job/42531085404"},{"completedAt":"2025-05-20T06:45:25Z","conclusion":"skipped","databaseId":42531085490,"name":"handle_failure","startedAt":"2025-05-20T06:45:26Z","status":"completed","steps":[],"url":"https://github.com/Ka0s-Klaus/ka0s/actions/runs/15130728901/job/42531085490"}],"name":"Ka0s Deploy Webs (Dashboard y Test)","number":348,"startedAt":"2025-05-20T06:45:03Z","status":"completed","updatedAt":"2025-05-20T06:45:43Z","url":"https://github.com/Ka0s-Klaus/ka0s/actions/runs/15130728901","workflowDatabaseId":153100219,"workflowName":"Ka0s Deploy Webs (Dashboard y Test)"}
