{"conclusion":"success","createdAt":"2025-05-28T11:20:05Z","databaseId":15298806798,"displayTitle":"Ka0s Create structure for FinOps","event":"workflow_dispatch","headBranch":"main","headSha":"a62dfc4a02ce6e7a47022f6a428c971ebda95d2d","jobs":[{"completedAt":"2025-05-28T11:20:15Z","conclusion":"success","databaseId":43034128248,"name":"job-core","startedAt":"2025-05-28T11:20:06Z","status":"completed","steps":[{"conclusion":"success","name":"Set up job","number":1,"status":"completed"},{"conclusion":"success","name":"Checkout repository","number":2,"status":"completed"},{"conclusion":"success","name":"Crear estructura FinOps HTML","number":3,"status":"completed"},{"conclusion":"success","name":"Upload Files","number":4,"status":"completed"},{"conclusion":"success","name":"Post Checkout repository","number":8,"status":"completed"},{"conclusion":"success","name":"Complete job","number":9,"status":"completed"}],"url":"https://github.com/Ka0s-Klaus/ka0s/actions/runs/15298806798/job/43034128248"},{"completedAt":"2025-05-28T11:20:24Z","conclusion":"success","databaseId":43034137931,"name":"handle-success","startedAt":"2025-05-28T11:20:17Z","status":"completed","steps":[{"conclusion":"success","name":"Set up job","number":1,"status":"completed"},{"conclusion":"success","name":"Checkout code","number":2,"status":"completed"},{"conclusion":"success","name":"handle-success-execution","number":3,"status":"completed"},{"conclusion":"success","name":"Post Checkout code","number":6,"status":"completed"},{"conclusion":"success","name":"Complete job","number":7,"status":"completed"}],"url":"https://github.com/Ka0s-Klaus/ka0s/actions/runs/15298806798/job/43034137931"},{"completedAt":"2025-05-28T11:20:33Z","conclusion":"success","databaseId":43034146258,"name":"end-workflow","startedAt":"2025-05-28T11:20:26Z","status":"completed","steps":[{"conclusion":"success","name":"Set up job","number":1,"status":"completed"},{"conclusion":"success","name":"Checkout code","number":2,"status":"completed"},{"conclusion":"success","name":"Finaliza el workflow","number":3,"status":"completed"},{"conclusion":"success","name":"Post Checkout code","number":6,"status":"completed"},{"conclusion":"success","name":"Complete job","number":7,"status":"completed"}],"url":"https://github.com/Ka0s-Klaus/ka0s/actions/runs/15298806798/job/43034146258"},{"completedAt":"2025-05-28T11:20:24Z","conclusion":"skipped","databaseId":43034146373,"name":"handle_failure","startedAt":"2025-05-28T11:20:24Z","status":"completed","steps":[],"url":"https://github.com/Ka0s-Klaus/ka0s/actions/runs/15298806798/job/43034146373"}],"name":"Ka0s Create structure for FinOps","number":39,"startedAt":"2025-05-28T11:20:05Z","status":"completed","updatedAt":"2025-05-28T11:20:33Z","url":"https://github.com/Ka0s-Klaus/ka0s/actions/runs/15298806798","workflowDatabaseId":164500248,"workflowName":"Ka0s Create structure for FinOps"}
