{"conclusion":"failure","createdAt":"2025-05-30T11:22:21Z","databaseId":15345661693,"displayTitle":"Ka0s Create structure for FinOps","event":"workflow_dispatch","headBranch":"main","headSha":"16cf1e3f7dd1d45a9f2cb6453a8e97350617d542","jobs":[{"completedAt":"2025-05-30T11:22:30Z","conclusion":"failure","databaseId":43181204248,"name":"job-core","startedAt":"2025-05-30T11:22:23Z","status":"completed","steps":[{"conclusion":"success","name":"Set up job","number":1,"status":"completed"},{"conclusion":"success","name":"Checkout repository","number":2,"status":"completed"},{"conclusion":"failure","name":"Crear estructura FinOps HTML","number":3,"status":"completed"},{"conclusion":"skipped","name":"Upload Files","number":4,"status":"completed"},{"conclusion":"success","name":"Post Checkout repository","number":8,"status":"completed"},{"conclusion":"success","name":"Complete job","number":9,"status":"completed"}],"url":"https://github.com/Ka0s-Klaus/ka0s/actions/runs/15345661693/job/43181204248"},{"completedAt":"2025-05-30T11:22:39Z","conclusion":"success","databaseId":43181212306,"name":"handle_failure","startedAt":"2025-05-30T11:22:32Z","status":"completed","steps":[{"conclusion":"success","name":"Set up job","number":1,"status":"completed"},{"conclusion":"success","name":"Checkout code","number":2,"status":"completed"},{"conclusion":"success","name":"handle-failure-execution","number":3,"status":"completed"},{"conclusion":"success","name":"Post Checkout code","number":6,"status":"completed"},{"conclusion":"success","name":"Complete job","number":7,"status":"completed"}],"url":"https://github.com/Ka0s-Klaus/ka0s/actions/runs/15345661693/job/43181212306"},{"completedAt":"2025-05-30T11:22:30Z","conclusion":"skipped","databaseId":43181212308,"name":"handle-success","startedAt":"2025-05-30T11:22:30Z","status":"completed","steps":[],"url":"https://github.com/Ka0s-Klaus/ka0s/actions/runs/15345661693/job/43181212308"},{"completedAt":"2025-05-30T11:22:48Z","conclusion":"success","databaseId":43181220924,"name":"end-workflow","startedAt":"2025-05-30T11:22:41Z","status":"completed","steps":[{"conclusion":"success","name":"Set up job","number":1,"status":"completed"},{"conclusion":"success","name":"Checkout code","number":2,"status":"completed"},{"conclusion":"success","name":"Finaliza el workflow","number":3,"status":"completed"},{"conclusion":"success","name":"Post Checkout code","number":6,"status":"completed"},{"conclusion":"success","name":"Complete job","number":7,"status":"completed"}],"url":"https://github.com/Ka0s-Klaus/ka0s/actions/runs/15345661693/job/43181220924"}],"name":"Ka0s Create structure for FinOps","number":104,"startedAt":"2025-05-30T11:22:21Z","status":"completed","updatedAt":"2025-05-30T11:22:49Z","url":"https://github.com/Ka0s-Klaus/ka0s/actions/runs/15345661693","workflowDatabaseId":164500248,"workflowName":"Ka0s Create structure for FinOps"}
