{"conclusion":"success","createdAt":"2025-02-20T11:02:21Z","databaseId":13433787431,"displayTitle":"Se modifica la extracción de ficheros involucrados","event":"push","headBranch":"H44-creación-módulo-versionado","headSha":"346d3e51b50979fa58f7c7c44a1d73ecd2a1624c","jobs":[{"completedAt":"2025-02-20T11:02:38Z","conclusion":"success","databaseId":37531367562,"name":"job-core","startedAt":"2025-02-20T11:02:28Z","status":"completed","steps":[{"conclusion":"success","name":"Set up job","number":1,"status":"completed"},{"conclusion":"success","name":"Checkout code","number":2,"status":"completed"},{"conclusion":"success","name":"Validate file extensions","number":3,"status":"completed"},{"conclusion":"success","name":"Crear JSON","number":4,"status":"completed"},{"conclusion":"success","name":"Set environment variable for ref","number":5,"status":"completed"},{"conclusion":"success","name":"Upload Files","number":6,"status":"completed"},{"conclusion":"success","name":"Ver JSON","number":7,"status":"completed"},{"conclusion":"success","name":"Run # Nuevo proceso de activacion de los modulos","number":8,"status":"completed"},{"conclusion":"success","name":"Post Checkout code","number":16,"status":"completed"},{"conclusion":"success","name":"Complete job","number":17,"status":"completed"}],"url":"https://github.com/Ka0s-Klaus/ka0s/actions/runs/13433787431/job/37531367562"},{"completedAt":"2025-02-20T11:02:49Z","conclusion":"success","databaseId":37531384302,"name":"handle-success","startedAt":"2025-02-20T11:02:44Z","status":"completed","steps":[{"conclusion":"success","name":"Set up job","number":1,"status":"completed"},{"conclusion":"success","name":"handle-success-execution","number":2,"status":"completed"},{"conclusion":"success","name":"Complete job","number":3,"status":"completed"}],"url":"https://github.com/Ka0s-Klaus/ka0s/actions/runs/13433787431/job/37531384302"},{"completedAt":"2025-02-20T11:02:50Z","conclusion":"skipped","databaseId":37531396617,"name":"handle_failure","startedAt":"2025-02-20T11:02:50Z","status":"completed","steps":[],"url":"https://github.com/Ka0s-Klaus/ka0s/actions/runs/13433787431/job/37531396617"},{"completedAt":"2025-02-20T11:03:03Z","conclusion":"success","databaseId":37531397562,"name":"end-workflow","startedAt":"2025-02-20T11:02:57Z","status":"completed","steps":[{"conclusion":"success","name":"Set up job","number":1,"status":"completed"},{"conclusion":"success","name":"Checkout code","number":2,"status":"completed"},{"conclusion":"success","name":"Finaliza el workflow","number":3,"status":"completed"},{"conclusion":"success","name":"Post Checkout code","number":6,"status":"completed"},{"conclusion":"success","name":"Complete job","number":7,"status":"completed"}],"url":"https://github.com/Ka0s-Klaus/ka0s/actions/runs/13433787431/job/37531397562"}],"name":"Ka0s","number":390,"startedAt":"2025-02-20T11:02:21Z","status":"completed","updatedAt":"2025-02-20T11:03:05Z","url":"https://github.com/Ka0s-Klaus/ka0s/actions/runs/13433787431","workflowDatabaseId":142022472,"workflowName":"Ka0s"}
