{"conclusion":"success","createdAt":"2025-04-03T08:48:28Z","databaseId":14238844999,"displayTitle":"Merge remote-tracking branch 'origin' into H220-web-de-resultados","event":"push","headBranch":"H220-web-de-resultados","headSha":"6ce74cb36708af6c45aec65fb521f4a175014a7c","jobs":[{"completedAt":"2025-04-03T08:50:35Z","conclusion":"success","databaseId":39903849378,"name":"job-core","startedAt":"2025-04-03T08:50:19Z","status":"completed","steps":[{"conclusion":"success","name":"Set up job","number":1,"status":"completed"},{"conclusion":"success","name":"Checkout code","number":2,"status":"completed"},{"conclusion":"success","name":"Validate file extensions","number":3,"status":"completed"},{"conclusion":"success","name":"Crear JSON","number":4,"status":"completed"},{"conclusion":"success","name":"Set environment variable for ref","number":5,"status":"completed"},{"conclusion":"success","name":"Upload Files","number":6,"status":"completed"},{"conclusion":"success","name":"Run git diff --name-only 7a4ddbd29669bf127665be85e6588c753e66fc85 6ce74cb36708af6c45aec65fb521f4a175014a7c > files-in-commit.txt","number":7,"status":"completed"},{"conclusion":"success","name":"Post Checkout code","number":14,"status":"completed"},{"conclusion":"success","name":"Complete job","number":15,"status":"completed"}],"url":"https://github.com/Ka0s-Klaus/ka0s/actions/runs/14238844999/job/39903849378"},{"completedAt":"2025-04-03T08:51:52Z","conclusion":"success","databaseId":39903980742,"name":"handle-success","startedAt":"2025-04-03T08:51:39Z","status":"completed","steps":[{"conclusion":"success","name":"Set up job","number":1,"status":"completed"},{"conclusion":"success","name":"Checkout code","number":2,"status":"completed"},{"conclusion":"success","name":"handle-success-execution","number":3,"status":"completed"},{"conclusion":"success","name":"Post Checkout code","number":6,"status":"completed"},{"conclusion":"success","name":"Complete job","number":7,"status":"completed"}],"url":"https://github.com/Ka0s-Klaus/ka0s/actions/runs/14238844999/job/39903980742"},{"completedAt":"2025-04-03T08:54:50Z","conclusion":"success","databaseId":39904061135,"name":"end-workflow","startedAt":"2025-04-03T08:52:43Z","status":"completed","steps":[{"conclusion":"success","name":"Set up job","number":1,"status":"completed"},{"conclusion":"success","name":"Checkout code","number":2,"status":"completed"},{"conclusion":"success","name":"Finaliza el workflow","number":3,"status":"completed"},{"conclusion":"success","name":"Post Checkout code","number":6,"status":"completed"},{"conclusion":"success","name":"Complete job","number":7,"status":"completed"}],"url":"https://github.com/Ka0s-Klaus/ka0s/actions/runs/14238844999/job/39904061135"},{"completedAt":"2025-04-03T08:51:52Z","conclusion":"skipped","databaseId":39904061210,"name":"handle_failure","startedAt":"2025-04-03T08:51:52Z","status":"completed","steps":[],"url":"https://github.com/Ka0s-Klaus/ka0s/actions/runs/14238844999/job/39904061210"}],"name":"Ka0s","number":917,"startedAt":"2025-04-03T08:48:28Z","status":"completed","updatedAt":"2025-04-03T08:54:51Z","url":"https://github.com/Ka0s-Klaus/ka0s/actions/runs/14238844999","workflowDatabaseId":142022472,"workflowName":"Ka0s"}
