{"conclusion":"success","createdAt":"2025-04-07T14:53:33Z","databaseId":14312440504,"displayTitle":"Merge branch 'H220-web-de-resultados' of https://github.com/Ka0s-Klau…","event":"push","headBranch":"H220-web-de-resultados","headSha":"3f5050766cd08b6febe366e3ad321a5a0fc84fe6","jobs":[{"completedAt":"2025-04-07T14:53:47Z","conclusion":"success","databaseId":40110526862,"name":"job-core","startedAt":"2025-04-07T14:53:35Z","status":"completed","steps":[{"conclusion":"success","name":"Set up job","number":1,"status":"completed"},{"conclusion":"success","name":"Checkout code","number":2,"status":"completed"},{"conclusion":"success","name":"Validate file extensions","number":3,"status":"completed"},{"conclusion":"success","name":"Crear JSON","number":4,"status":"completed"},{"conclusion":"success","name":"Set environment variable for ref","number":5,"status":"completed"},{"conclusion":"success","name":"Upload Files","number":6,"status":"completed"},{"conclusion":"success","name":"Run git diff --name-only 510076c161fe86f69cff6531d54da4abb0fe4dda 3f5050766cd08b6febe366e3ad321a5a0fc84fe6 > files-in-commit.txt","number":7,"status":"completed"},{"conclusion":"success","name":"Post Checkout code","number":14,"status":"completed"},{"conclusion":"success","name":"Complete job","number":15,"status":"completed"}],"url":"https://github.com/Ka0s-Klaus/ka0s/actions/runs/14312440504/job/40110526862"},{"completedAt":"2025-04-07T14:54:11Z","conclusion":"success","databaseId":40110542592,"name":"handle-success","startedAt":"2025-04-07T14:53:53Z","status":"completed","steps":[{"conclusion":"success","name":"Set up job","number":1,"status":"completed"},{"conclusion":"success","name":"Checkout code","number":2,"status":"completed"},{"conclusion":"success","name":"handle-success-execution","number":3,"status":"completed"},{"conclusion":"success","name":"Post Checkout code","number":6,"status":"completed"},{"conclusion":"success","name":"Complete job","number":7,"status":"completed"}],"url":"https://github.com/Ka0s-Klaus/ka0s/actions/runs/14312440504/job/40110542592"},{"completedAt":"2025-04-07T14:54:19Z","conclusion":"success","databaseId":40110570491,"name":"end-workflow","startedAt":"2025-04-07T14:54:12Z","status":"completed","steps":[{"conclusion":"success","name":"Set up job","number":1,"status":"completed"},{"conclusion":"success","name":"Checkout code","number":2,"status":"completed"},{"conclusion":"success","name":"Finaliza el workflow","number":3,"status":"completed"},{"conclusion":"success","name":"Post Checkout code","number":6,"status":"completed"},{"conclusion":"success","name":"Complete job","number":7,"status":"completed"}],"url":"https://github.com/Ka0s-Klaus/ka0s/actions/runs/14312440504/job/40110570491"},{"completedAt":"2025-04-07T14:54:11Z","conclusion":"skipped","databaseId":40110570744,"name":"handle_failure","startedAt":"2025-04-07T14:54:11Z","status":"completed","steps":[],"url":"https://github.com/Ka0s-Klaus/ka0s/actions/runs/14312440504/job/40110570744"}],"name":"Ka0s","number":1054,"startedAt":"2025-04-07T14:53:33Z","status":"completed","updatedAt":"2025-04-07T14:54:20Z","url":"https://github.com/Ka0s-Klaus/ka0s/actions/runs/14312440504","workflowDatabaseId":142022472,"workflowName":"Ka0s"}
