{"conclusion":"failure","createdAt":"2025-04-07T14:26:30Z","databaseId":14311819998,"displayTitle":"Merge remote-tracking branch 'origin' into H220-web-de-resultados","event":"push","headBranch":"H220-web-de-resultados","headSha":"2adfc935339cba33fde3cd41de836c114a684795","jobs":[{"completedAt":"2025-04-07T14:29:07Z","conclusion":"failure","databaseId":40108455678,"name":"job-core","startedAt":"2025-04-07T14:26:33Z","status":"completed","steps":[{"conclusion":"success","name":"Set up job","number":1,"status":"completed"},{"conclusion":"success","name":"Checkout code","number":2,"status":"completed"},{"conclusion":"success","name":"Validate file extensions","number":3,"status":"completed"},{"conclusion":"success","name":"Crear JSON","number":4,"status":"completed"},{"conclusion":"success","name":"Set environment variable for ref","number":5,"status":"completed"},{"conclusion":"failure","name":"Upload Files","number":6,"status":"completed"},{"conclusion":"skipped","name":"Run git diff --name-only 8e751fe1a35c8a7c77a9a3f02e6766bfb892c24d 2adfc935339cba33fde3cd41de836c114a684795 > files-in-commit.txt","number":7,"status":"completed"},{"conclusion":"success","name":"Post Checkout code","number":14,"status":"completed"},{"conclusion":"success","name":"Complete job","number":15,"status":"completed"}],"url":"https://github.com/Ka0s-Klaus/ka0s/actions/runs/14311819998/job/40108455678"},{"completedAt":"2025-04-07T14:29:07Z","conclusion":"skipped","databaseId":40108658491,"name":"handle-success","startedAt":"2025-04-07T14:29:07Z","status":"completed","steps":[],"url":"https://github.com/Ka0s-Klaus/ka0s/actions/runs/14311819998/job/40108658491"},{"completedAt":"2025-04-07T14:29:49Z","conclusion":"success","databaseId":40108658507,"name":"handle_failure","startedAt":"2025-04-07T14:29:22Z","status":"completed","steps":[{"conclusion":"success","name":"Set up job","number":1,"status":"completed"},{"conclusion":"success","name":"Checkout code","number":2,"status":"completed"},{"conclusion":"success","name":"handle-failure-execution","number":3,"status":"completed"},{"conclusion":"success","name":"Post Checkout code","number":6,"status":"completed"},{"conclusion":"success","name":"Complete job","number":7,"status":"completed"}],"url":"https://github.com/Ka0s-Klaus/ka0s/actions/runs/14311819998/job/40108658507"},{"completedAt":"2025-04-07T14:30:36Z","conclusion":"success","databaseId":40108713364,"name":"end-workflow","startedAt":"2025-04-07T14:29:51Z","status":"completed","steps":[{"conclusion":"success","name":"Set up job","number":1,"status":"completed"},{"conclusion":"success","name":"Checkout code","number":2,"status":"completed"},{"conclusion":"success","name":"Finaliza el workflow","number":3,"status":"completed"},{"conclusion":"success","name":"Post Checkout code","number":6,"status":"completed"},{"conclusion":"success","name":"Complete job","number":7,"status":"completed"}],"url":"https://github.com/Ka0s-Klaus/ka0s/actions/runs/14311819998/job/40108713364"}],"name":"Ka0s","number":1047,"startedAt":"2025-04-07T14:26:30Z","status":"completed","updatedAt":"2025-04-07T14:30:37Z","url":"https://github.com/Ka0s-Klaus/ka0s/actions/runs/14311819998","workflowDatabaseId":142022472,"workflowName":"Ka0s"}
