{"conclusion":"success","createdAt":"2025-04-19T01:13:40Z","databaseId":14544206272,"displayTitle":"Ka0s Workflow Statistics Summary","event":"schedule","headBranch":"main","headSha":"b050aeebceb5ae0340a5fc248c7c949e062fcad7","jobs":[{"completedAt":"2025-04-19T01:19:00Z","conclusion":"success","databaseId":40807326246,"name":"job-core","startedAt":"2025-04-19T01:13:42Z","status":"completed","steps":[{"conclusion":"success","name":"Set up job","number":1,"status":"completed"},{"conclusion":"success","name":"Checkout repository","number":2,"status":"completed"},{"conclusion":"success","name":"Collect workflow statistics","number":3,"status":"completed"},{"conclusion":"success","name":"Commit and push changes","number":4,"status":"completed"},{"conclusion":"success","name":"Post Checkout repository","number":8,"status":"completed"},{"conclusion":"success","name":"Complete job","number":9,"status":"completed"}],"url":"https://github.com/Ka0s-Klaus/ka0s/actions/runs/14544206272/job/40807326246"},{"completedAt":"2025-04-19T01:19:16Z","conclusion":"success","databaseId":40807432080,"name":"job-stats","startedAt":"2025-04-19T01:19:02Z","status":"completed","steps":[{"conclusion":"success","name":"Set up job","number":1,"status":"completed"},{"conclusion":"success","name":"Checkout repository","number":2,"status":"completed"},{"conclusion":"success","name":"Generate workflow names","number":3,"status":"completed"},{"conclusion":"success","name":"Generate repository statistics","number":4,"status":"completed"},{"conclusion":"success","name":"Generate Issues Summary","number":5,"status":"completed"},{"conclusion":"success","name":"Commit statistics","number":6,"status":"completed"},{"conclusion":"success","name":"Post Checkout repository","number":12,"status":"completed"},{"conclusion":"success","name":"Complete job","number":13,"status":"completed"}],"url":"https://github.com/Ka0s-Klaus/ka0s/actions/runs/14544206272/job/40807432080"},{"completedAt":"2025-04-19T01:19:24Z","conclusion":"success","databaseId":40807437267,"name":"handle-success","startedAt":"2025-04-19T01:19:17Z","status":"completed","steps":[{"conclusion":"success","name":"Set up job","number":1,"status":"completed"},{"conclusion":"success","name":"Checkout code","number":2,"status":"completed"},{"conclusion":"success","name":"handle-success-execution","number":3,"status":"completed"},{"conclusion":"success","name":"Post Checkout code","number":6,"status":"completed"},{"conclusion":"success","name":"Complete job","number":7,"status":"completed"}],"url":"https://github.com/Ka0s-Klaus/ka0s/actions/runs/14544206272/job/40807437267"},{"completedAt":"2025-04-19T01:19:32Z","conclusion":"success","databaseId":40807439372,"name":"end-workflow","startedAt":"2025-04-19T01:19:25Z","status":"completed","steps":[{"conclusion":"success","name":"Set up job","number":1,"status":"completed"},{"conclusion":"success","name":"Checkout code","number":2,"status":"completed"},{"conclusion":"success","name":"Finaliza el workflow","number":3,"status":"completed"},{"conclusion":"success","name":"Post Checkout code","number":6,"status":"completed"},{"conclusion":"success","name":"Complete job","number":7,"status":"completed"}],"url":"https://github.com/Ka0s-Klaus/ka0s/actions/runs/14544206272/job/40807439372"},{"completedAt":"2025-04-19T01:19:24Z","conclusion":"skipped","databaseId":40807439412,"name":"handle_failure","startedAt":"2025-04-19T01:19:24Z","status":"completed","steps":[],"url":"https://github.com/Ka0s-Klaus/ka0s/actions/runs/14544206272/job/40807439412"}],"name":"Ka0s Workflow Statistics Summary","number":74,"startedAt":"2025-04-19T01:13:40Z","status":"completed","updatedAt":"2025-04-19T01:19:32Z","url":"https://github.com/Ka0s-Klaus/ka0s/actions/runs/14544206272","workflowDatabaseId":153261529,"workflowName":"Ka0s Workflow Statistics Summary"}
