{"conclusion":"success","createdAt":"2025-04-24T08:14:09Z","databaseId":14636748078,"displayTitle":"Cambios en nombre archivos json","event":"push","headBranch":"H220-web-de-resultados","headSha":"927b9ba1f05a5a269a9647c2a376bf65bfd52c8c","jobs":[{"completedAt":"2025-04-24T08:14:22Z","conclusion":"success","databaseId":41069519822,"name":"job-core","startedAt":"2025-04-24T08:14:11Z","status":"completed","steps":[{"conclusion":"success","name":"Set up job","number":1,"status":"completed"},{"conclusion":"success","name":"Checkout code","number":2,"status":"completed"},{"conclusion":"success","name":"Validate file extensions","number":3,"status":"completed"},{"conclusion":"success","name":"Crear JSON","number":4,"status":"completed"},{"conclusion":"success","name":"Upload Files","number":5,"status":"completed"},{"conclusion":"success","name":"Run git diff --name-only 39bbee760130b01c3776ba47ccddad050a8e3559 927b9ba1f05a5a269a9647c2a376bf65bfd52c8c > files-in-commit.txt","number":6,"status":"completed"},{"conclusion":"success","name":"Post Checkout code","number":12,"status":"completed"},{"conclusion":"success","name":"Complete job","number":13,"status":"completed"}],"url":"https://github.com/Ka0s-Klaus/ka0s/actions/runs/14636748078/job/41069519822"},{"completedAt":"2025-04-24T08:14:31Z","conclusion":"success","databaseId":41069532098,"name":"handle-success","startedAt":"2025-04-24T08:14:23Z","status":"completed","steps":[{"conclusion":"success","name":"Set up job","number":1,"status":"completed"},{"conclusion":"success","name":"Checkout code","number":2,"status":"completed"},{"conclusion":"success","name":"handle-success-execution","number":3,"status":"completed"},{"conclusion":"success","name":"Post Checkout code","number":6,"status":"completed"},{"conclusion":"success","name":"Complete job","number":7,"status":"completed"}],"url":"https://github.com/Ka0s-Klaus/ka0s/actions/runs/14636748078/job/41069532098"},{"completedAt":"2025-04-24T08:14:40Z","conclusion":"success","databaseId":41069540947,"name":"end-workflow","startedAt":"2025-04-24T08:14:33Z","status":"completed","steps":[{"conclusion":"success","name":"Set up job","number":1,"status":"completed"},{"conclusion":"success","name":"Checkout code","number":2,"status":"completed"},{"conclusion":"success","name":"Finaliza el workflow","number":3,"status":"completed"},{"conclusion":"success","name":"Post Checkout code","number":6,"status":"completed"},{"conclusion":"success","name":"Complete job","number":7,"status":"completed"}],"url":"https://github.com/Ka0s-Klaus/ka0s/actions/runs/14636748078/job/41069540947"},{"completedAt":"2025-04-24T08:14:32Z","conclusion":"skipped","databaseId":41069540967,"name":"handle_failure","startedAt":"2025-04-24T08:14:32Z","status":"completed","steps":[],"url":"https://github.com/Ka0s-Klaus/ka0s/actions/runs/14636748078/job/41069540967"}],"name":"Ka0s","number":1342,"startedAt":"2025-04-24T08:14:09Z","status":"completed","updatedAt":"2025-04-24T08:14:41Z","url":"https://github.com/Ka0s-Klaus/ka0s/actions/runs/14636748078","workflowDatabaseId":142022472,"workflowName":"Ka0s"}
