{"conclusion":"success","createdAt":"2025-05-14T15:07:53Z","databaseId":15024325752,"displayTitle":"Ka0s Create structure for dashboard","event":"workflow_dispatch","headBranch":"main","headSha":"6470221b15750d7571a6b6fd9623a3296a6253a3","jobs":[{"completedAt":"2025-05-14T15:08:06Z","conclusion":"success","databaseId":42221189998,"name":"job-core","startedAt":"2025-05-14T15:07:55Z","status":"completed","steps":[{"conclusion":"success","name":"Set up job","number":1,"status":"completed"},{"conclusion":"success","name":"Checkout repository","number":2,"status":"completed"},{"conclusion":"success","name":"Copy web folder structure","number":3,"status":"completed"},{"conclusion":"success","name":"Upload Files","number":4,"status":"completed"},{"conclusion":"success","name":"Post Checkout repository","number":8,"status":"completed"},{"conclusion":"success","name":"Complete job","number":9,"status":"completed"}],"url":"https://github.com/Ka0s-Klaus/ka0s/actions/runs/15024325752/job/42221189998"},{"completedAt":"2025-05-14T15:08:21Z","conclusion":"success","databaseId":42221206825,"name":"job-data","startedAt":"2025-05-14T15:08:08Z","status":"completed","steps":[{"conclusion":"success","name":"Set up job","number":1,"status":"completed"},{"conclusion":"success","name":"Checkout repository","number":2,"status":"completed"},{"conclusion":"success","name":"Copy data files to web structure","number":3,"status":"completed"},{"conclusion":"success","name":"Copiar archivos JSON de config/webs a data","number":4,"status":"completed"},{"conclusion":"success","name":"Upload Files","number":5,"status":"completed"},{"conclusion":"success","name":"Post Checkout repository","number":10,"status":"completed"},{"conclusion":"success","name":"Complete job","number":11,"status":"completed"}],"url":"https://github.com/Ka0s-Klaus/ka0s/actions/runs/15024325752/job/42221206825"},{"completedAt":"2025-05-14T15:08:41Z","conclusion":"success","databaseId":42221229370,"name":"job-design","startedAt":"2025-05-14T15:08:22Z","status":"completed","steps":[{"conclusion":"success","name":"Set up job","number":1,"status":"completed"},{"conclusion":"success","name":"Checkout repository","number":2,"status":"completed"},{"conclusion":"success","name":"Preparar directorios y copiar archivos estáticos","number":3,"status":"completed"},{"conclusion":"success","name":"Generar HTML de secciones","number":4,"status":"completed"},{"conclusion":"success","name":"Crear dashboard.html","number":5,"status":"completed"},{"conclusion":"success","name":"Crear test.html","number":6,"status":"completed"},{"conclusion":"success","name":"Guardar cambios en el repositorio","number":7,"status":"completed"},{"conclusion":"success","name":"Post Checkout repository","number":14,"status":"completed"},{"conclusion":"success","name":"Complete job","number":15,"status":"completed"}],"url":"https://github.com/Ka0s-Klaus/ka0s/actions/runs/15024325752/job/42221229370"},{"completedAt":"2025-05-14T15:09:01Z","conclusion":"success","databaseId":42221255744,"name":"handle-success","startedAt":"2025-05-14T15:08:52Z","status":"completed","steps":[{"conclusion":"success","name":"Set up job","number":1,"status":"completed"},{"conclusion":"success","name":"Checkout code","number":2,"status":"completed"},{"conclusion":"success","name":"handle-success-execution","number":3,"status":"completed"},{"conclusion":"success","name":"Post Checkout code","number":6,"status":"completed"},{"conclusion":"success","name":"Complete job","number":7,"status":"completed"}],"url":"https://github.com/Ka0s-Klaus/ka0s/actions/runs/15024325752/job/42221255744"},{"completedAt":"2025-05-14T15:09:18Z","conclusion":"success","databaseId":42221282890,"name":"end-workflow","startedAt":"2025-05-14T15:09:10Z","status":"completed","steps":[{"conclusion":"success","name":"Set up job","number":1,"status":"completed"},{"conclusion":"success","name":"Checkout code","number":2,"status":"completed"},{"conclusion":"success","name":"Finaliza el workflow","number":3,"status":"completed"},{"conclusion":"success","name":"Post Checkout code","number":6,"status":"completed"},{"conclusion":"success","name":"Complete job","number":7,"status":"completed"}],"url":"https://github.com/Ka0s-Klaus/ka0s/actions/runs/15024325752/job/42221282890"},{"completedAt":"2025-05-14T15:09:01Z","conclusion":"skipped","databaseId":42221283045,"name":"handle_failure","startedAt":"2025-05-14T15:09:01Z","status":"completed","steps":[],"url":"https://github.com/Ka0s-Klaus/ka0s/actions/runs/15024325752/job/42221283045"}],"name":"Ka0s Create structure for dashboard","number":307,"startedAt":"2025-05-14T15:07:53Z","status":"completed","updatedAt":"2025-05-14T15:09:19Z","url":"https://github.com/Ka0s-Klaus/ka0s/actions/runs/15024325752","workflowDatabaseId":155387840,"workflowName":"Ka0s Create structure for dashboard"}
