{"conclusion":"success","createdAt":"2025-05-19T14:58:33Z","databaseId":15116378415,"displayTitle":"subida inicial de web FinOps","event":"push","headBranch":"H1183-personalización-módulo-finops","headSha":"832ca83bd9e2f2489b28ce4cd20af6b1895f1ea8","jobs":[{"completedAt":"2025-05-19T14:59:01Z","conclusion":"success","databaseId":42488009117,"name":"job-core","startedAt":"2025-05-19T14:58:35Z","status":"completed","steps":[{"conclusion":"success","name":"Set up job","number":1,"status":"completed"},{"conclusion":"success","name":"Checkout code","number":2,"status":"completed"},{"conclusion":"success","name":"Validate file extensions","number":3,"status":"completed"},{"conclusion":"success","name":"Crear JSON","number":4,"status":"completed"},{"conclusion":"success","name":"Upload Files","number":5,"status":"completed"},{"conclusion":"success","name":"Run git diff --name-only adf44615a0e6f61d32c327691f33aec3a337e098 832ca83bd9e2f2489b28ce4cd20af6b1895f1ea8 > files-in-commit.txt","number":6,"status":"completed"},{"conclusion":"success","name":"Post Checkout code","number":12,"status":"completed"},{"conclusion":"success","name":"Complete job","number":13,"status":"completed"}],"url":"https://github.com/Ka0s-Klaus/ka0s/actions/runs/15116378415/job/42488009117"},{"completedAt":"2025-05-19T14:59:10Z","conclusion":"success","databaseId":42488043490,"name":"handle-success","startedAt":"2025-05-19T14:59:02Z","status":"completed","steps":[{"conclusion":"success","name":"Set up job","number":1,"status":"completed"},{"conclusion":"success","name":"Checkout code","number":2,"status":"completed"},{"conclusion":"success","name":"handle-success-execution","number":3,"status":"completed"},{"conclusion":"success","name":"Post Checkout code","number":6,"status":"completed"},{"conclusion":"success","name":"Complete job","number":7,"status":"completed"}],"url":"https://github.com/Ka0s-Klaus/ka0s/actions/runs/15116378415/job/42488043490"},{"completedAt":"2025-05-19T14:59:21Z","conclusion":"success","databaseId":42488056074,"name":"end-workflow","startedAt":"2025-05-19T14:59:12Z","status":"completed","steps":[{"conclusion":"success","name":"Set up job","number":1,"status":"completed"},{"conclusion":"success","name":"Checkout code","number":2,"status":"completed"},{"conclusion":"success","name":"Finaliza el workflow","number":3,"status":"completed"},{"conclusion":"success","name":"Post Checkout code","number":6,"status":"completed"},{"conclusion":"success","name":"Complete job","number":7,"status":"completed"}],"url":"https://github.com/Ka0s-Klaus/ka0s/actions/runs/15116378415/job/42488056074"},{"completedAt":"2025-05-19T14:59:11Z","conclusion":"skipped","databaseId":42488056371,"name":"handle_failure","startedAt":"2025-05-19T14:59:11Z","status":"completed","steps":[],"url":"https://github.com/Ka0s-Klaus/ka0s/actions/runs/15116378415/job/42488056371"}],"name":"Ka0s","number":1696,"startedAt":"2025-05-19T14:58:33Z","status":"completed","updatedAt":"2025-05-19T14:59:22Z","url":"https://github.com/Ka0s-Klaus/ka0s/actions/runs/15116378415","workflowDatabaseId":142022472,"workflowName":"Ka0s"}
