{"conclusion":"failure","createdAt":"2025-05-28T10:42:04Z","databaseId":15298086844,"displayTitle":"Ka0s Create structure for FinOps","event":"workflow_dispatch","headBranch":"main","headSha":"98660ad18349e54bba8dc119623091405ba201da","jobs":[{"completedAt":"2025-05-28T10:42:13Z","conclusion":"failure","databaseId":43031842904,"name":"job-core","startedAt":"2025-05-28T10:42:06Z","status":"completed","steps":[{"conclusion":"success","name":"Set up job","number":1,"status":"completed"},{"conclusion":"success","name":"Checkout repository","number":2,"status":"completed"},{"conclusion":"failure","name":"Crear estructura FinOps HTML","number":3,"status":"completed"},{"conclusion":"skipped","name":"Upload Files","number":4,"status":"completed"},{"conclusion":"success","name":"Post Checkout repository","number":8,"status":"completed"},{"conclusion":"success","name":"Complete job","number":9,"status":"completed"}],"url":"https://github.com/Ka0s-Klaus/ka0s/actions/runs/15298086844/job/43031842904"},{"completedAt":"2025-05-28T10:42:23Z","conclusion":"success","databaseId":43031852971,"name":"handle_failure","startedAt":"2025-05-28T10:42:15Z","status":"completed","steps":[{"conclusion":"success","name":"Set up job","number":1,"status":"completed"},{"conclusion":"success","name":"Checkout code","number":2,"status":"completed"},{"conclusion":"success","name":"handle-failure-execution","number":3,"status":"completed"},{"conclusion":"success","name":"Post Checkout code","number":6,"status":"completed"},{"conclusion":"success","name":"Complete job","number":7,"status":"completed"}],"url":"https://github.com/Ka0s-Klaus/ka0s/actions/runs/15298086844/job/43031852971"},{"completedAt":"2025-05-28T10:42:13Z","conclusion":"skipped","databaseId":43031853014,"name":"handle-success","startedAt":"2025-05-28T10:42:13Z","status":"completed","steps":[],"url":"https://github.com/Ka0s-Klaus/ka0s/actions/runs/15298086844/job/43031853014"},{"completedAt":"2025-05-28T10:42:33Z","conclusion":"success","databaseId":43031863316,"name":"end-workflow","startedAt":"2025-05-28T10:42:25Z","status":"completed","steps":[{"conclusion":"success","name":"Set up job","number":1,"status":"completed"},{"conclusion":"success","name":"Checkout code","number":2,"status":"completed"},{"conclusion":"success","name":"Finaliza el workflow","number":3,"status":"completed"},{"conclusion":"success","name":"Post Checkout code","number":6,"status":"completed"},{"conclusion":"success","name":"Complete job","number":7,"status":"completed"}],"url":"https://github.com/Ka0s-Klaus/ka0s/actions/runs/15298086844/job/43031863316"}],"name":"Ka0s Create structure for FinOps","number":35,"startedAt":"2025-05-28T10:42:04Z","status":"completed","updatedAt":"2025-05-28T10:42:33Z","url":"https://github.com/Ka0s-Klaus/ka0s/actions/runs/15298086844","workflowDatabaseId":164500248,"workflowName":"Ka0s Create structure for FinOps"}
