{"conclusion":"success","createdAt":"2025-06-26T07:45:41Z","databaseId":15896032536,"displayTitle":"Ka0s Markdown Lint","event":"workflow_dispatch","headBranch":"H1224-new-module-mongodb","headSha":"a9da116b16570328e35b3f080933b18163de1dd0","jobs":[{"completedAt":"2025-06-26T07:45:58Z","conclusion":"success","databaseId":44827694154,"name":"job-core","startedAt":"2025-06-26T07:45:43Z","status":"completed","steps":[{"conclusion":"success","name":"Set up job","number":1,"status":"completed"},{"conclusion":"success","name":"Run actions/checkout@v4","number":2,"status":"completed"},{"conclusion":"success","name":"Run actions/setup-node@v4","number":3,"status":"completed"},{"conclusion":"success","name":"Run npm install -g markdownlint-cli2","number":4,"status":"completed"},{"conclusion":"success","name":"Run # Realizamos el check del documento md ","number":5,"status":"completed"},{"conclusion":"success","name":"Post Run actions/setup-node@v4","number":9,"status":"completed"},{"conclusion":"success","name":"Post Run actions/checkout@v4","number":10,"status":"completed"},{"conclusion":"success","name":"Complete job","number":11,"status":"completed"}],"url":"https://github.com/Ka0s-Klaus/ka0s/actions/runs/15896032536/job/44827694154"},{"completedAt":"2025-06-26T07:46:07Z","conclusion":"success","databaseId":44827711319,"name":"handle-success","startedAt":"2025-06-26T07:45:59Z","status":"completed","steps":[{"conclusion":"success","name":"Set up job","number":1,"status":"completed"},{"conclusion":"success","name":"Checkout code","number":2,"status":"completed"},{"conclusion":"success","name":"handle-success-execution","number":3,"status":"completed"},{"conclusion":"success","name":"Post Checkout code","number":6,"status":"completed"},{"conclusion":"success","name":"Complete job","number":7,"status":"completed"}],"url":"https://github.com/Ka0s-Klaus/ka0s/actions/runs/15896032536/job/44827711319"},{"completedAt":"2025-06-26T07:46:17Z","conclusion":"success","databaseId":44827721299,"name":"end-workflow","startedAt":"2025-06-26T07:46:09Z","status":"completed","steps":[{"conclusion":"success","name":"Set up job","number":1,"status":"completed"},{"conclusion":"success","name":"Checkout code","number":2,"status":"completed"},{"conclusion":"success","name":"Finaliza el workflow","number":3,"status":"completed"},{"conclusion":"success","name":"Post Checkout code","number":6,"status":"completed"},{"conclusion":"success","name":"Complete job","number":7,"status":"completed"}],"url":"https://github.com/Ka0s-Klaus/ka0s/actions/runs/15896032536/job/44827721299"},{"completedAt":"2025-06-26T07:46:07Z","conclusion":"skipped","databaseId":44827721324,"name":"handle_failure","startedAt":"2025-06-26T07:46:08Z","status":"completed","steps":[],"url":"https://github.com/Ka0s-Klaus/ka0s/actions/runs/15896032536/job/44827721324"}],"name":"Ka0s Markdown Lint","number":196,"startedAt":"2025-06-26T07:45:41Z","status":"completed","updatedAt":"2025-06-26T07:46:18Z","url":"https://github.com/Ka0s-Klaus/ka0s/actions/runs/15896032536","workflowDatabaseId":142215142,"workflowName":"Ka0s Markdown Lint"}
