{
  "timestamp": "2026-02-19T15:58:35.894422Z",
  "github_event": "issue_comment",
  "github_action": "created",
  "github_repo": "Ka0s-Klaus/ka0s",
  "github_ref": "https://github.com/Ka0s-Klaus/ka0s/issues/4170",
  "operation": "add_comment",
  "itop_class": "UserRequest",
  "itop_key": "134",
  "update": {
    "status": "ok",
    "response": {
      "code": 0,
      "message": null,
      "objects": {
        "UserRequest::134": {
          "code": 0,
          "message": "updated",
          "class": "UserRequest",
          "key": "134",
          "fields": {
            "operational_status": "ongoing",
            "ref": "R-000170",
            "org_id": "1",
            "org_name": "Ka0s Inc",
            "caller_id": "0",
            "caller_name": "",
            "team_id": "0",
            "team_name": "",
            "team_email": "",
            "agent_id": "0",
            "agent_name": "",
            "title": "[GH:#4170 Ka0s-Klaus/ka0s] Flujo detallado zabbix - github",
            "description": "<p>Resumen: Flujo detallado zabbix - github\n\n---\nDescripcion original (GitHub):\n\nEsta es la tarjeta donde tendreis que trabajar los cuatro:\n- Conocer cada uno de los campos que se rellenan cuando zabbix detecta un incidente de tipo High\n- Modificar la template de incidencia con los campos que zabbix indique\n- Documentar la template de incidencia\n- workflow que cree una incidencia basandose en esta template y pasando los valores de las variables\n\n---\nOrigen: GitHub\nIssue: https://github.com/Ka0s-Klaus/ka0s/issues/4170\nRepo: Ka0s-Klaus/ka0s\n</p>",
            "start_date": "2026-02-19 11:43:24",
            "end_date": "",
            "last_update": "2026-02-19 16:58:36",
            "close_date": "",
            "private_log": {
              "entries": []
            },
            "contacts_list": [],
            "functionalcis_list": [],
            "workorders_list": [],
            "status": "new",
            "request_type": "service_request",
            "impact": "1",
            "priority": "4",
            "urgency": "4",
            "origin": "phone",
            "approver_id": "0",
            "approver_email": "",
            "service_id": "0",
            "service_name": "",
            "servicesubcategory_id": "0",
            "servicesubcategory_name": "",
            "escalation_flag": "no",
            "escalation_reason": "",
            "assignment_date": "",
            "resolution_date": "",
            "last_pending_date": "",
            "cumulatedpending": 0,
            "tto": 0,
            "ttr": 0,
            "tto_escalation_deadline": "",
            "sla_tto_passed": "no",
            "sla_tto_over": null,
            "ttr_escalation_deadline": "",
            "sla_ttr_passed": "no",
            "sla_ttr_over": null,
            "time_spent": "",
            "resolution_code": "assistance",
            "solution": "",
            "pending_reason": "",
            "parent_request_id": "0",
            "parent_request_ref": "",
            "parent_incident_id": "0",
            "parent_incident_ref": "",
            "parent_problem_id": "0",
            "parent_problem_ref": "",
            "parent_change_id": "0",
            "parent_change_ref": "",
            "related_request_list": [],
            "public_log": {
              "entries": [
                {
                  "date": "2026-02-19 12:18:11",
                  "user_login": "Github iTop",
                  "user_id": "8",
                  "message": "GitHub issues/edited: https://github.com/Ka0s-Klaus/ka0s/issues/4170",
                  "message_html": "GitHub issues/edited: https://github.com/Ka0s-Klaus/ka0s/issues/4170"
                },
                {
                  "date": "2026-02-19 16:38:45",
                  "user_login": "Github iTop",
                  "user_id": "8",
                  "message": "GitHub issues/edited: https://github.com/Ka0s-Klaus/ka0s/issues/4170",
                  "message_html": "GitHub issues/edited: https://github.com/Ka0s-Klaus/ka0s/issues/4170"
                },
                {
                  "date": "2026-02-19 16:58:36",
                  "user_login": "Github iTop",
                  "user_id": "8",
                  "message": "Comentario de GitHub por AdrianLozanoMartinez:\n\nHe a\u00f1adido los campos: hosts, trigger, severity\n\n\nhttps://github.com/Ka0s-Klaus/ka0s/issues/4170",
                  "message_html": "Comentario de GitHub por AdrianLozanoMartinez:<br/><br/>He a\u00f1adido los campos: hosts, trigger, severity<br/><br/><br/>https://github.com/Ka0s-Klaus/ka0s/issues/4170"
                }
              ]
            },
            "user_satisfaction": "1",
            "user_comment": "",
            "finalclass": "UserRequest",
            "friendlyname": "R-000170",
            "org_id_friendlyname": "Ka0s Inc",
            "org_id_obsolescence_flag": "",
            "caller_id_friendlyname": "",
            "caller_id_obsolescence_flag": "",
            "team_id_friendlyname": "",
            "team_id_obsolescence_flag": "",
            "agent_id_friendlyname": "",
            "agent_id_obsolescence_flag": "",
            "approver_id_friendlyname": "",
            "approver_id_obsolescence_flag": "",
            "service_id_friendlyname": "",
            "servicesubcategory_id_friendlyname": "",
            "parent_request_id_friendlyname": "",
            "parent_incident_id_friendlyname": "",
            "parent_problem_id_friendlyname": "",
            "parent_change_id_friendlyname": "",
            "parent_change_id_finalclass_recall": ""
          }
        }
      }
    }
  }
}
