{
  "summary": {
    "total_runs": 408,
    "successful_runs": 331,
    "failed_runs": 70,
    "cancelled_runs": 3,
    "success_rate": 81,
    "failure_rate": 17,
    "average_duration": 297.19607843137254,
    "average_success_duration": 110.66465256797584,
    "average_failed_duration": 263.5857142857143,
    "average_cancelled_duration": 22056.666666666668
  },
  "workflow_distribution": {
    "Ka0s Deploy Webs (Dashboard y Test)": 169,
    "Ka0s Deploy Webs": 177,
    "Deploy Dashboard to Web Server": 62
  },
  "event_distribution": {
    "push": 330,
    "workflow_dispatch": 78
  }
}
