{
  "summary": {
    "total_runs": 1248,
    "successful_runs": 557,
    "failed_runs": 111,
    "cancelled_runs": 4,
    "success_rate": 44,
    "failure_rate": 8,
    "average_duration": 622.9831730769231,
    "average_success_duration": 429.45960502693,
    "average_failed_duration": 2006.0720720720722,
    "average_cancelled_duration": 78565.75
  },
  "workflow_distribution": {
    "Ka0s": 1248
  },
  "event_distribution": {
    "push": 1187,
    "pull_request": 32,
    "issues": 20,
    "issue_comment": 8,
    "workflow_dispatch": 1
  }
}
