{
  "event_type": "push",
  "trigger_branch": "refs/heads/H1183-personalización-módulo-finops",
  "timestamp": "2025-05-22T14:08:09Z",
  "author": {
    "name": "jh0ny2k2",
    "email": "117847861+jh0ny2k2@users.noreply.github.com"
  },
[
{"sha":"2c1c3f29d1d1b0df838922e39f2ef61e8d3ac88a","author":"jh0ny2k2","email":"developerjhony@gmail.com","date":"2025-05-22T16:07:41+02:00","message":"Merge branch 'H1183-personalización-módulo-finops' of https://github.com/Ka0s-Klaus/ka0s into H1183-personalización-módulo-finops"},
{"sha":"3f8274918bc079eb9ba21bceb15baf9e0250702d","author":"jh0ny2k2","email":"developerjhony@gmail.com","date":"2025-05-22T16:07:06+02:00","message":"Revert "[Ka0S] Uploading resume execution files to the repository...""},
{"sha":"5740a421b78da0508fd1c0be75d173bb3b122588","author":"jh0ny2k2","email":"developerjhony@gmail.com","date":"2025-05-22T16:05:38+02:00","message":"Revert "cambios de json""}]
[
"core/config/finops/results/data/Section/section1.json"
,
"core/config/finops/webs/js/template.js"
,
"core/results/k/event_data_15184082753.json"
,
"core/results/k/event_data_15184082753.json.bak"
]
}
